{
	"topics": [
		{
			"label": "Introduction to COBOL",
			"description": "Get your bearings: program structure, data declaration, and the four divisions.",
			"links": [
				{
					"type": "tutorial",
					"id": "COBOLIntro",
					"file": "COBOLIntro.html",
					"title": "The Structure of COBOL Programs"
				},
				{
					"type": "tutorial",
					"id": "DataDeclaration",
					"file": "DataDeclaration.html",
					"title": "Declaring Data in COBOL"
				},
				{
					"type": "tutorial",
					"id": "COBOLcommands",
					"file": "COBOLcommands.html",
					"title": "Basic Procedure Division Commands"
				},
				{
					"type": "exercise",
					"file": "../exercises/GettingStarted.html",
					"title": "Getting Started"
				}
			]
		},
		{
			"label": "COBOL Control Structures",
			"description": "Branch and loop: IF, EVALUATE, and PERFORM in all its forms.",
			"links": [
				{
					"type": "tutorial",
					"id": "Selection",
					"file": "Selection.html",
					"title": "Selection in COBOL"
				},
				{
					"type": "tutorial",
					"id": "Iteration",
					"file": "Iteration.html",
					"title": "Iteration in COBOL"
				},
				{
					"type": "exercise",
					"file": "../exercises/CountDown.html",
					"title": "The Calculator and Countdown Exercise"
				}
			]
		},
		{
			"label": "Simple Sequential Files",
			"description": "Read and process file records one at a time — the bread-and-butter pattern for batch COBOL.",
			"links": [
				{
					"type": "tutorial",
					"id": "SequentialFiles1",
					"file": "SequentialFiles1.html",
					"title": "Introduction to Sequential Files"
				},
				{
					"type": "tutorial",
					"id": "SequentialFiles2",
					"file": "SequentialFiles2.html",
					"title": "Processing Sequential Files"
				},
				{
					"type": "exercise",
					"file": "../exercises/SeqRead.html",
					"title": "Reading Sequential Files"
				},
				{
					"type": "exercise",
					"file": "../exercises/SeqReadIf.html",
					"title": "Counting Records in a Sequential File"
				}
			]
		},
		{
			"label": "Advanced Data Declaration",
			"description": "Edited PICTURE strings and the USAGE clause for richer data representations.",
			"links": [
				{
					"type": "tutorial",
					"id": "EditedPics",
					"file": "EditedPics.html",
					"title": "Edited Pictures"
				},
				{
					"type": "tutorial",
					"id": "Usage",
					"file": "Usage.html",
					"title": "The USAGE Clause"
				},
				{
					"type": "exercise",
					"file": "../exercises/SeqWrite.html",
					"title": "Writing Records to a Sequential File"
				},
				{
					"type": "exercise",
					"file": "../exercises/SeqInsert.html",
					"title": "Inserting Records in a Sequential File"
				}
			]
		},
		{
			"label": "Advanced Sequential Files",
			"description": "Print files, variable-length records, sorting, merging, and in-place updates.",
			"links": [
				{
					"type": "tutorial",
					"id": "SequentialFiles3",
					"file": "SequentialFiles3.html",
					"title": "COBOL Print Files and Variable-Length Records"
				},
				{
					"type": "tutorial",
					"id": "SortMerge",
					"file": "SortMerge.html",
					"title": "Sorting and Merging"
				},
				{
					"type": "tutorial",
					"id": "COBOLcommands",
					"file": "COBOLcommands.html",
					"title": "Basic Procedure Division Commands"
				},
				{
					"type": "exercise",
					"file": "../exercises/SeqUpdate.html",
					"title": "Updating a Sequential File"
				},
				{
					"type": "exercise",
					"file": "../exercises/SortIP.html",
					"title": "Sorting a Sequential File"
				}
			]
		},
		{
			"label": "Direct Access Files",
			"description": "Random-access alternatives to sequential files: relative and indexed organisations.",
			"links": [
				{
					"type": "tutorial",
					"id": "Intro2DirectAccess",
					"file": "Intro2DirectAccess.html",
					"title": "Introduction to Direct Access Files"
				},
				{
					"type": "tutorial",
					"id": "RelativeFiles",
					"file": "RelativeFiles.html",
					"title": "Relative Files"
				},
				{
					"type": "tutorial",
					"id": "IndexedFiles",
					"file": "IndexedFiles.html",
					"title": "Indexed Files"
				}
			]
		},
		{
			"label": "COBOL Tables",
			"description": "Arrays in COBOL — declaring tables, accessing them, and searching with SEARCH / SEARCH ALL.",
			"links": [
				{
					"type": "tutorial",
					"id": "Tables1",
					"file": "Tables1.html",
					"title": "Using Tables"
				},
				{
					"type": "tutorial",
					"id": "Tables2",
					"file": "Tables2.html",
					"title": "Creating Tables - Syntax and Semantics"
				},
				{
					"type": "tutorial",
					"id": "Search",
					"file": "Search.html",
					"title": "Searching Tables"
				},
				{
					"type": "exercise",
					"file": "../exercises/MonthTable.html",
					"title": "Using Tables"
				}
			]
		},
		{
			"label": "Constructing Large Systems",
			"description": "Splitting a program across source files: sub-programs and the COPY verb.",
			"links": [
				{
					"type": "tutorial",
					"id": "Subprograms",
					"file": "Subprograms.html",
					"title": "Contained and External Sub-Programs"
				},
				{
					"type": "tutorial",
					"id": "Copy",
					"file": "Copy.html",
					"title": "The COPY Verb"
				}
			]
		},
		{
			"label": "COBOL String Handling",
			"description": "Operate on character data: INSPECT, STRING, UNSTRING, reference modification, and intrinsic functions.",
			"links": [
				{
					"type": "tutorial",
					"id": "Inspect",
					"file": "Inspect.html",
					"title": "INSPECT"
				},
				{
					"type": "tutorial",
					"id": "String",
					"file": "String.html",
					"title": "STRING"
				},
				{
					"type": "tutorial",
					"id": "Unstring",
					"file": "Unstring.html",
					"title": "UNSTRING"
				},
				{
					"type": "tutorial",
					"id": "RefMod",
					"file": "RefMod.html",
					"title": "Reference Modification and Intrinsic Functions"
				}
			]
		},
		{
			"label": "The COBOL Report Writer",
			"description": "COBOL's built-in reporting facility — by example first, then by syntax and semantics.",
			"links": [
				{
					"type": "tutorial",
					"id": "ReportWriter",
					"file": "ReportWriter.html",
					"title": "Report Writer by Example"
				},
				{
					"type": "tutorial",
					"id": "ReportWriterSS",
					"file": "ReportWriterSS.html",
					"title": "Report Writer Syntax and Semantics"
				}
			]
		},
		{
			"label": "Reference",
			"description": "Quick lookup for keywords and concepts encountered across the course.",
			"links": [
				{
					"type": "reference",
					"file": "glossary.html",
					"title": "Glossary of COBOL Keywords and Concepts"
				}
			]
		}
	]
}
